pelicun/__init__.py
pelicun/assessment.py
pelicun/auto.py
pelicun/base.py
pelicun/cli.py
pelicun/file_io.py
pelicun/pelicun_warnings.py
pelicun/uq.py
pelicun/examples/001/CMP_QNT.csv
pelicun/examples/001/demands_s4.csv
pelicun/examples/001/input.json
pelicun/examples/002/CMP_QNT.csv
pelicun/examples/002/input.json
pelicun/examples/002/response.csv
pelicun/examples/0_tmp/CMP_marginals.csv
pelicun/examples/0_tmp/DMG_process_P58.json
pelicun/examples/0_tmp/LOSS_map.csv
pelicun/examples/0_tmp/config.json
pelicun/examples/0_tmp/demands.csv
pelicun/examples/0_tmp/fragility_Additional.csv
pelicun/examples/0_tmp/repair_Additional.csv
pelicun/model/__init__.py
pelicun/model/asset_model.py
pelicun/model/damage_model.py
pelicun/model/demand_model.py
pelicun/model/loss_model.py
pelicun/model/pelicun_model.py
pelicun/resources/dlml_resource_paths.json
pelicun/settings/default_config.json
pelicun/settings/default_units.json
pelicun/settings/input_schema.json
pelicun/tests/__init__.py
pelicun/tests/code_repetition_checker.py
pelicun/tests/conftest.py
pelicun/tests/util.py
pelicun/tests/basic/__init__.py
pelicun/tests/basic/reset_tests.py
pelicun/tests/basic/test_assessment.py
pelicun/tests/basic/test_asset_model.py
pelicun/tests/basic/test_auto.py
pelicun/tests/basic/test_base.py
pelicun/tests/basic/test_cli_logging.py
pelicun/tests/basic/test_damage_model.py
pelicun/tests/basic/test_demand_model.py
pelicun/tests/basic/test_file_io.py
pelicun/tests/basic/test_loss_model.py
pelicun/tests/basic/test_model.py
pelicun/tests/basic/test_pelicun_model.py
pelicun/tests/basic/test_uq.py
pelicun/tests/basic/data/assessment/test_assessment_calc_unit_scale_factor/custom_units.json
pelicun/tests/basic/data/base/test_parse_units/additional_units_a.json
pelicun/tests/basic/data/base/test_parse_units/duplicate.json
pelicun/tests/basic/data/base/test_parse_units/duplicate2.json
pelicun/tests/basic/data/base/test_parse_units/invalid.json
pelicun/tests/basic/data/base/test_parse_units/not_dict.json
pelicun-3.8.1.post1.dist-info/licenses/LICENSE
pelicun-3.8.1.post1.dist-info/METADATA
pelicun-3.8.1.post1.dist-info/WHEEL
pelicun-3.8.1.post1.dist-info/entry_points.txt
pelicun-3.8.1.post1.dist-info/top_level.txt
pelicun-3.8.1.post1.dist-info/RECORD
