Metadata-Version: 2.4
Name: pelicun
Version: 3.8.1.post1
Summary: Probabilistic Estimation of Losses, Injuries, and Community resilience Under Natural hazard events
Author-email: Adam Zsarnóczay <adamzs@stanford.edu>
License: BSD-3-Clause
Project-URL: Homepage, http://nheri-simcenter.github.io/pelicun/
Classifier: Programming Language :: Python
Classifier: Development Status :: 5 - Production/Stable
Classifier: Natural Language :: English
Classifier: Environment :: Console
Classifier: Framework :: Jupyter
Classifier: Intended Audience :: Education
Classifier: Intended Audience :: Science/Research
Classifier: Natural Language :: English
Classifier: Operating System :: Microsoft :: Windows
Classifier: Operating System :: MacOS :: MacOS X
Classifier: Operating System :: Unix
Classifier: Programming Language :: Python :: 3.9
Classifier: Programming Language :: Python :: 3.10
Classifier: Programming Language :: Python :: 3.11
Classifier: Programming Language :: Python :: 3.12
Classifier: Topic :: Scientific/Engineering
License-File: LICENSE
Requires-Dist: numpy<2.0,>=1.22.0
Requires-Dist: scipy<=1.15.3,>=1.7.0
Requires-Dist: pandas<3.0,>=1.4.0
Requires-Dist: colorama<0.5.0,>=0.4.0
Requires-Dist: numexpr<3.0,>=2.8
Requires-Dist: jsonschema<5.0,>=4.22.0
Requires-Dist: tqdm
Requires-Dist: requests
Requires-Dist: joblib
Requires-Dist: scikit-learn
Requires-Dist: packaging
Provides-Extra: development
Requires-Dist: codespell; extra == "development"
Requires-Dist: flake8; extra == "development"
Requires-Dist: flake8-bugbear; extra == "development"
Requires-Dist: flake8-rst; extra == "development"
Requires-Dist: flake8-rst; extra == "development"
Requires-Dist: flake8-rst-docstrings; extra == "development"
Requires-Dist: glob2; extra == "development"
Requires-Dist: jsonpath2; extra == "development"
Requires-Dist: jupyter; extra == "development"
Requires-Dist: jupytext; extra == "development"
Requires-Dist: mypy; extra == "development"
Requires-Dist: nbsphinx; extra == "development"
Requires-Dist: numpydoc; extra == "development"
Requires-Dist: pandas-stubs; extra == "development"
Requires-Dist: pydocstyle; extra == "development"
Requires-Dist: pylint; extra == "development"
Requires-Dist: pylint-pytest; extra == "development"
Requires-Dist: pytest; extra == "development"
Requires-Dist: pytest-cov; extra == "development"
Requires-Dist: pytest-httpserver; extra == "development"
Requires-Dist: pytest-socket; extra == "development"
Requires-Dist: pytest-xdist; extra == "development"
Requires-Dist: rendre>0.0.14; extra == "development"
Requires-Dist: ruff==0.7.0; extra == "development"
Requires-Dist: sphinx; extra == "development"
Requires-Dist: sphinx-autoapi; extra == "development"
Requires-Dist: sphinx-rtd-theme; extra == "development"
Requires-Dist: sphinx_design; extra == "development"
Requires-Dist: sphinxcontrib-bibtex; extra == "development"
Requires-Dist: types-colorama; extra == "development"
Dynamic: license-file
